lightpandas/__init__.py
lightpandas/core_api.py
lightpandas/dataframe.py
light_pandas-0.1.22.dist-info/METADATA
light_pandas-0.1.22.dist-info/WHEEL
light_pandas-0.1.22.dist-info/top_level.txt
light_pandas-0.1.22.dist-info/RECORD
