Metadata-Version: 2.1
Name: light-pandas
Version: 0.1.22
Summary: Light weight Pandas library
Home-page: https://github.com/bombhero/LightPandas
Author: bomb_hero
Author-email: bomb.zhang@gmail.com
License: MIT
